{
  "swagger": "2.0",
  "info": {
    "title": "",
    "description": "",
    "version": ""
  },
  "host": "stephane-bressani.ch:8000",
  "schemes": [
    "http"
  ],
  "paths": {
    "/api/astrology_birth_theme": {
      "get": {
        "operationId": "astrology_birth_theme_list",
        "responses": {
          "200": {
            "description": ""
          }
        },
        "parameters": [
          {
            "name": "year_month_day",
            "required": true,
            "in": "query",
            "description": "Year/Month/Day of birth format as : yyyy/mm/dd",
            "type": "string"
          },
          {
            "name": "hour_min",
            "required": true,
            "in": "query",
            "description": "Hour:Minute of birth format as : hh:mm",
            "type": "string"
          },
          {
            "name": "utc",
            "required": true,
            "in": "query",
            "description": "Utc of birth format as : +hh:mm",
            "type": "string"
          },
          {
            "name": "geo_pos_ns",
            "required": true,
            "in": "query",
            "description": "Geo pos Nord/Sud as HxM : _n_or _s_",
            "type": "string"
          },
          {
            "name": "geo_pos_we",
            "required": true,
            "in": "query",
            "description": "Geo pos Est/West as HxM : _e_or _w_",
            "type": "string"
          }
        ],
        "description": "Get astrology birth theme with astro_py",
        "summary": "Get astrology birth theme with astro_py",
        "tags": [
          "api"
        ]
      }
    },
    "/api/swagger": {
      "get": {
        "operationId": "swagger_list",
        "responses": {
          "200": {
            "description": ""
          }
        },
        "parameters": [],
        "description": "Api for swagger",
        "summary": "Api for swagger",
        "tags": [
          "api"
        ]
      }
    },
    "/test/": {
      "get": {
        "operationId": "list",
        "responses": {
          "200": {
            "description": ""
          }
        },
        "parameters": [],
        "tags": [
          "test"
        ]
      }
    }
  },
  "securityDefinitions": {
    "basic": {
      "type": "basic"
    }
  }
}